<?xml version="1.0" encoding="utf-8"?>
<NodeSet xmlns:i="http://www.w3.org/2001/XMLSchema-instance" xmlns="http://opcfoundation.org/UA/2008/02/Types.xsd">
  <NamespaceUris>
    <String>http://opcfoundation.org/UA/</String>
    <String>http://opcfoundation.org/OPCUAServer</String>
  </NamespaceUris>
  <ServerUris />
  <Nodes>
    <Node i:type="ObjectNode">
      <NodeId>
        <Identifier>ns=1;i=1</Identifier>
      </NodeId>
      <NodeClass>Object_1</NodeClass>
      <BrowseName>
        <NamespaceIndex>1</NamespaceIndex>
        <Name>MySystem</Name>
      </BrowseName>
      <DisplayName>
        <Locale></Locale>
        <Text>MySystem</Text>
      </DisplayName>
      <Description i:nil="true" />
      <WriteMask>0</WriteMask>
      <UserWriteMask>0</UserWriteMask>
      <RolePermissions />
      <UserRolePermissions />
      <AccessRestrictions>0</AccessRestrictions>
      <References>
        <ReferenceNode>
          <ReferenceTypeId>
            <Identifier>i=40</Identifier>
          </ReferenceTypeId>
          <IsInverse>false</IsInverse>
          <TargetId>
            <Identifier>i=58</Identifier>
          </TargetId>
        </ReferenceNode>
        <ReferenceNode>
          <ReferenceTypeId>
            <Identifier>i=35</Identifier>
          </ReferenceTypeId>
          <IsInverse>true</IsInverse>
          <TargetId>
            <Identifier>i=85</Identifier>
          </TargetId>
        </ReferenceNode>
        <ReferenceNode>
          <ReferenceTypeId>
            <Identifier>i=47</Identifier>
          </ReferenceTypeId>
          <IsInverse>false</IsInverse>
          <TargetId>
            <Identifier>ns=1;i=2</Identifier>
          </TargetId>
        </ReferenceNode>
        <ReferenceNode>
          <ReferenceTypeId>
            <Identifier>i=47</Identifier>
          </ReferenceTypeId>
          <IsInverse>false</IsInverse>
          <TargetId>
            <Identifier>ns=1;i=10</Identifier>
          </TargetId>
        </ReferenceNode>
        <ReferenceNode>
          <ReferenceTypeId>
            <Identifier>i=47</Identifier>
          </ReferenceTypeId>
          <IsInverse>false</IsInverse>
          <TargetId>
            <Identifier>ns=1;i=18</Identifier>
          </TargetId>
        </ReferenceNode>
      </References>
      <EventNotifier>0</EventNotifier>
    </Node>
    <Node i:type="ObjectNode">
      <NodeId>
        <Identifier>ns=1;i=2</Identifier>
      </NodeId>
      <NodeClass>Object_1</NodeClass>
      <BrowseName>
        <NamespaceIndex>1</NamespaceIndex>
        <Name>Motor1</Name>
      </BrowseName>
      <DisplayName>
        <Locale></Locale>
        <Text>Motor1</Text>
      </DisplayName>
      <Description i:nil="true" />
      <WriteMask>0</WriteMask>
      <UserWriteMask>0</UserWriteMask>
      <RolePermissions />
      <UserRolePermissions />
      <AccessRestrictions>0</AccessRestrictions>
      <References>
        <ReferenceNode>
          <ReferenceTypeId>
            <Identifier>i=47</Identifier>
          </ReferenceTypeId>
          <IsInverse>true</IsInverse>
          <TargetId>
            <Identifier>ns=1;i=1</Identifier>
          </TargetId>
        </ReferenceNode>
        <ReferenceNode>
          <ReferenceTypeId>
            <Identifier>i=40</Identifier>
          </ReferenceTypeId>
          <IsInverse>false</IsInverse>
          <TargetId>
            <Identifier>i=58</Identifier>
          </TargetId>
        </ReferenceNode>
        <ReferenceNode>
          <ReferenceTypeId>
            <Identifier>i=47</Identifier>
          </ReferenceTypeId>
          <IsInverse>false</IsInverse>
          <TargetId>
            <Identifier>ns=1;i=3</Identifier>
          </TargetId>
        </ReferenceNode>
        <ReferenceNode>
          <ReferenceTypeId>
            <Identifier>i=47</Identifier>
          </ReferenceTypeId>
          <IsInverse>false</IsInverse>
          <TargetId>
            <Identifier>ns=1;i=4</Identifier>
          </TargetId>
        </ReferenceNode>
        <ReferenceNode>
          <ReferenceTypeId>
            <Identifier>i=47</Identifier>
          </ReferenceTypeId>
          <IsInverse>false</IsInverse>
          <TargetId>
            <Identifier>ns=1;i=5</Identifier>
          </TargetId>
        </ReferenceNode>
        <ReferenceNode>
          <ReferenceTypeId>
            <Identifier>i=47</Identifier>
          </ReferenceTypeId>
          <IsInverse>false</IsInverse>
          <TargetId>
            <Identifier>ns=1;i=6</Identifier>
          </TargetId>
        </ReferenceNode>
        <ReferenceNode>
          <ReferenceTypeId>
            <Identifier>i=47</Identifier>
          </ReferenceTypeId>
          <IsInverse>false</IsInverse>
          <TargetId>
            <Identifier>ns=1;i=7</Identifier>
          </TargetId>
        </ReferenceNode>
        <ReferenceNode>
          <ReferenceTypeId>
            <Identifier>i=47</Identifier>
          </ReferenceTypeId>
          <IsInverse>false</IsInverse>
          <TargetId>
            <Identifier>ns=1;i=8</Identifier>
          </TargetId>
        </ReferenceNode>
        <ReferenceNode>
          <ReferenceTypeId>
            <Identifier>i=47</Identifier>
          </ReferenceTypeId>
          <IsInverse>false</IsInverse>
          <TargetId>
            <Identifier>ns=1;i=9</Identifier>
          </TargetId>
        </ReferenceNode>
      </References>
      <EventNotifier>0</EventNotifier>
    </Node>
    <Node i:type="VariableNode">
      <NodeId>
        <Identifier>ns=1;i=3</Identifier>
      </NodeId>
      <NodeClass>Variable_2</NodeClass>
      <BrowseName>
        <NamespaceIndex>1</NamespaceIndex>
        <Name>Start</Name>
      </BrowseName>
      <DisplayName>
        <Locale></Locale>
        <Text>Start</Text>
      </DisplayName>
      <Description i:nil="true" />
      <WriteMask>0</WriteMask>
      <UserWriteMask>0</UserWriteMask>
      <RolePermissions />
      <UserRolePermissions />
      <AccessRestrictions>0</AccessRestrictions>
      <References>
        <ReferenceNode>
          <ReferenceTypeId>
            <Identifier>i=47</Identifier>
          </ReferenceTypeId>
          <IsInverse>true</IsInverse>
          <TargetId>
            <Identifier>ns=1;i=2</Identifier>
          </TargetId>
        </ReferenceNode>
        <ReferenceNode>
          <ReferenceTypeId>
            <Identifier>i=40</Identifier>
          </ReferenceTypeId>
          <IsInverse>false</IsInverse>
          <TargetId>
            <Identifier>i=63</Identifier>
          </TargetId>
        </ReferenceNode>
      </References>
      <Value>
        <Value>
          <Boolean xmlns="http://opcfoundation.org/UA/2008/02/Types.xsd">false</Boolean>
        </Value>
      </Value>
      <DataType>
        <Identifier>i=1</Identifier>
      </DataType>
      <ValueRank>-1</ValueRank>
      <ArrayDimensions />
      <AccessLevel>3</AccessLevel>
      <UserAccessLevel>3</UserAccessLevel>
      <MinimumSamplingInterval>0</MinimumSamplingInterval>
      <Historizing>false</Historizing>
      <AccessLevelEx>0</AccessLevelEx>
    </Node>
    <Node i:type="VariableNode">
      <NodeId>
        <Identifier>ns=1;i=4</Identifier>
      </NodeId>
      <NodeClass>Variable_2</NodeClass>
      <BrowseName>
        <NamespaceIndex>1</NamespaceIndex>
        <Name>Stop</Name>
      </BrowseName>
      <DisplayName>
        <Locale></Locale>
        <Text>Stop</Text>
      </DisplayName>
      <Description i:nil="true" />
      <WriteMask>0</WriteMask>
      <UserWriteMask>0</UserWriteMask>
      <RolePermissions />
      <UserRolePermissions />
      <AccessRestrictions>0</AccessRestrictions>
      <References>
        <ReferenceNode>
          <ReferenceTypeId>
            <Identifier>i=47</Identifier>
          </ReferenceTypeId>
          <IsInverse>true</IsInverse>
          <TargetId>
            <Identifier>ns=1;i=2</Identifier>
          </TargetId>
        </ReferenceNode>
        <ReferenceNode>
          <ReferenceTypeId>
            <Identifier>i=40</Identifier>
          </ReferenceTypeId>
          <IsInverse>false</IsInverse>
          <TargetId>
            <Identifier>i=63</Identifier>
          </TargetId>
        </ReferenceNode>
      </References>
      <Value>
        <Value>
          <Boolean xmlns="http://opcfoundation.org/UA/2008/02/Types.xsd">false</Boolean>
        </Value>
      </Value>
      <DataType>
        <Identifier>i=1</Identifier>
      </DataType>
      <ValueRank>-1</ValueRank>
      <ArrayDimensions />
      <AccessLevel>3</AccessLevel>
      <UserAccessLevel>3</UserAccessLevel>
      <MinimumSamplingInterval>0</MinimumSamplingInterval>
      <Historizing>false</Historizing>
      <AccessLevelEx>0</AccessLevelEx>
    </Node>
    <Node i:type="VariableNode">
      <NodeId>
        <Identifier>ns=1;i=5</Identifier>
      </NodeId>
      <NodeClass>Variable_2</NodeClass>
      <BrowseName>
        <NamespaceIndex>1</NamespaceIndex>
        <Name>Run</Name>
      </BrowseName>
      <DisplayName>
        <Locale></Locale>
        <Text>Run</Text>
      </DisplayName>
      <Description i:nil="true" />
      <WriteMask>0</WriteMask>
      <UserWriteMask>0</UserWriteMask>
      <RolePermissions />
      <UserRolePermissions />
      <AccessRestrictions>0</AccessRestrictions>
      <References>
        <ReferenceNode>
          <ReferenceTypeId>
            <Identifier>i=47</Identifier>
          </ReferenceTypeId>
          <IsInverse>true</IsInverse>
          <TargetId>
            <Identifier>ns=1;i=2</Identifier>
          </TargetId>
        </ReferenceNode>
        <ReferenceNode>
          <ReferenceTypeId>
            <Identifier>i=40</Identifier>
          </ReferenceTypeId>
          <IsInverse>false</IsInverse>
          <TargetId>
            <Identifier>i=63</Identifier>
          </TargetId>
        </ReferenceNode>
      </References>
      <Value>
        <Value>
          <Boolean xmlns="http://opcfoundation.org/UA/2008/02/Types.xsd">false</Boolean>
        </Value>
      </Value>
      <DataType>
        <Identifier>i=1</Identifier>
      </DataType>
      <ValueRank>-1</ValueRank>
      <ArrayDimensions />
      <AccessLevel>3</AccessLevel>
      <UserAccessLevel>3</UserAccessLevel>
      <MinimumSamplingInterval>0</MinimumSamplingInterval>
      <Historizing>false</Historizing>
      <AccessLevelEx>0</AccessLevelEx>
    </Node>
    <Node i:type="VariableNode">
      <NodeId>
        <Identifier>ns=1;i=6</Identifier>
      </NodeId>
      <NodeClass>Variable_2</NodeClass>
      <BrowseName>
        <NamespaceIndex>1</NamespaceIndex>
        <Name>Power</Name>
      </BrowseName>
      <DisplayName>
        <Locale></Locale>
        <Text>Power</Text>
      </DisplayName>
      <Description i:nil="true" />
      <WriteMask>0</WriteMask>
      <UserWriteMask>0</UserWriteMask>
      <RolePermissions />
      <UserRolePermissions />
      <AccessRestrictions>0</AccessRestrictions>
      <References>
        <ReferenceNode>
          <ReferenceTypeId>
            <Identifier>i=47</Identifier>
          </ReferenceTypeId>
          <IsInverse>true</IsInverse>
          <TargetId>
            <Identifier>ns=1;i=2</Identifier>
          </TargetId>
        </ReferenceNode>
        <ReferenceNode>
          <ReferenceTypeId>
            <Identifier>i=40</Identifier>
          </ReferenceTypeId>
          <IsInverse>false</IsInverse>
          <TargetId>
            <Identifier>i=63</Identifier>
          </TargetId>
        </ReferenceNode>
      </References>
      <Value>
        <Value>
          <Float xmlns="http://opcfoundation.org/UA/2008/02/Types.xsd">0</Float>
        </Value>
      </Value>
      <DataType>
        <Identifier>i=10</Identifier>
      </DataType>
      <ValueRank>-1</ValueRank>
      <ArrayDimensions />
      <AccessLevel>3</AccessLevel>
      <UserAccessLevel>3</UserAccessLevel>
      <MinimumSamplingInterval>0</MinimumSamplingInterval>
      <Historizing>false</Historizing>
      <AccessLevelEx>0</AccessLevelEx>
    </Node>
    <Node i:type="VariableNode">
      <NodeId>
        <Identifier>ns=1;i=7</Identifier>
      </NodeId>
      <NodeClass>Variable_2</NodeClass>
      <BrowseName>
        <NamespaceIndex>1</NamespaceIndex>
        <Name>PowerMax</Name>
      </BrowseName>
      <DisplayName>
        <Locale></Locale>
        <Text>PowerMax</Text>
      </DisplayName>
      <Description i:nil="true" />
      <WriteMask>0</WriteMask>
      <UserWriteMask>0</UserWriteMask>
      <RolePermissions />
      <UserRolePermissions />
      <AccessRestrictions>0</AccessRestrictions>
      <References>
        <ReferenceNode>
          <ReferenceTypeId>
            <Identifier>i=47</Identifier>
          </ReferenceTypeId>
          <IsInverse>true</IsInverse>
          <TargetId>
            <Identifier>ns=1;i=2</Identifier>
          </TargetId>
        </ReferenceNode>
        <ReferenceNode>
          <ReferenceTypeId>
            <Identifier>i=40</Identifier>
          </ReferenceTypeId>
          <IsInverse>false</IsInverse>
          <TargetId>
            <Identifier>i=63</Identifier>
          </TargetId>
        </ReferenceNode>
      </References>
      <Value>
        <Value>
          <Float xmlns="http://opcfoundation.org/UA/2008/02/Types.xsd">0</Float>
        </Value>
      </Value>
      <DataType>
        <Identifier>i=10</Identifier>
      </DataType>
      <ValueRank>-1</ValueRank>
      <ArrayDimensions />
      <AccessLevel>3</AccessLevel>
      <UserAccessLevel>3</UserAccessLevel>
      <MinimumSamplingInterval>0</MinimumSamplingInterval>
      <Historizing>false</Historizing>
      <AccessLevelEx>0</AccessLevelEx>
    </Node>
    <Node i:type="VariableNode">
      <NodeId>
        <Identifier>ns=1;i=8</Identifier>
      </NodeId>
      <NodeClass>Variable_2</NodeClass>
      <BrowseName>
        <NamespaceIndex>1</NamespaceIndex>
        <Name>Speed</Name>
      </BrowseName>
      <DisplayName>
        <Locale></Locale>
        <Text>Speed</Text>
      </DisplayName>
      <Description i:nil="true" />
      <WriteMask>0</WriteMask>
      <UserWriteMask>0</UserWriteMask>
      <RolePermissions />
      <UserRolePermissions />
      <AccessRestrictions>0</AccessRestrictions>
      <References>
        <ReferenceNode>
          <ReferenceTypeId>
            <Identifier>i=47</Identifier>
          </ReferenceTypeId>
          <IsInverse>true</IsInverse>
          <TargetId>
            <Identifier>ns=1;i=2</Identifier>
          </TargetId>
        </ReferenceNode>
        <ReferenceNode>
          <ReferenceTypeId>
            <Identifier>i=40</Identifier>
          </ReferenceTypeId>
          <IsInverse>false</IsInverse>
          <TargetId>
            <Identifier>i=63</Identifier>
          </TargetId>
        </ReferenceNode>
      </References>
      <Value>
        <Value>
          <UInt16 xmlns="http://opcfoundation.org/UA/2008/02/Types.xsd">0</UInt16>
        </Value>
      </Value>
      <DataType>
        <Identifier>i=5</Identifier>
      </DataType>
      <ValueRank>-1</ValueRank>
      <ArrayDimensions />
      <AccessLevel>3</AccessLevel>
      <UserAccessLevel>3</UserAccessLevel>
      <MinimumSamplingInterval>0</MinimumSamplingInterval>
      <Historizing>false</Historizing>
      <AccessLevelEx>0</AccessLevelEx>
    </Node>
    <Node i:type="VariableNode">
      <NodeId>
        <Identifier>ns=1;i=9</Identifier>
      </NodeId>
      <NodeClass>Variable_2</NodeClass>
      <BrowseName>
        <NamespaceIndex>1</NamespaceIndex>
        <Name>SpeedMax</Name>
      </BrowseName>
      <DisplayName>
        <Locale></Locale>
        <Text>SpeedMax</Text>
      </DisplayName>
      <Description i:nil="true" />
      <WriteMask>0</WriteMask>
      <UserWriteMask>0</UserWriteMask>
      <RolePermissions />
      <UserRolePermissions />
      <AccessRestrictions>0</AccessRestrictions>
      <References>
        <ReferenceNode>
          <ReferenceTypeId>
            <Identifier>i=47</Identifier>
          </ReferenceTypeId>
          <IsInverse>true</IsInverse>
          <TargetId>
            <Identifier>ns=1;i=2</Identifier>
          </TargetId>
        </ReferenceNode>
        <ReferenceNode>
          <ReferenceTypeId>
            <Identifier>i=40</Identifier>
          </ReferenceTypeId>
          <IsInverse>false</IsInverse>
          <TargetId>
            <Identifier>i=63</Identifier>
          </TargetId>
        </ReferenceNode>
      </References>
      <Value>
        <Value>
          <UInt16 xmlns="http://opcfoundation.org/UA/2008/02/Types.xsd">0</UInt16>
        </Value>
      </Value>
      <DataType>
        <Identifier>i=5</Identifier>
      </DataType>
      <ValueRank>-1</ValueRank>
      <ArrayDimensions />
      <AccessLevel>3</AccessLevel>
      <UserAccessLevel>3</UserAccessLevel>
      <MinimumSamplingInterval>0</MinimumSamplingInterval>
      <Historizing>false</Historizing>
      <AccessLevelEx>0</AccessLevelEx>
    </Node>
    <Node i:type="ObjectNode">
      <NodeId>
        <Identifier>ns=1;i=10</Identifier>
      </NodeId>
      <NodeClass>Object_1</NodeClass>
      <BrowseName>
        <NamespaceIndex>1</NamespaceIndex>
        <Name>Motor2</Name>
      </BrowseName>
      <DisplayName>
        <Locale></Locale>
        <Text>Motor2</Text>
      </DisplayName>
      <Description i:nil="true" />
      <WriteMask>0</WriteMask>
      <UserWriteMask>0</UserWriteMask>
      <RolePermissions />
      <UserRolePermissions />
      <AccessRestrictions>0</AccessRestrictions>
      <References>
        <ReferenceNode>
          <ReferenceTypeId>
            <Identifier>i=47</Identifier>
          </ReferenceTypeId>
          <IsInverse>true</IsInverse>
          <TargetId>
            <Identifier>ns=1;i=1</Identifier>
          </TargetId>
        </ReferenceNode>
        <ReferenceNode>
          <ReferenceTypeId>
            <Identifier>i=40</Identifier>
          </ReferenceTypeId>
          <IsInverse>false</IsInverse>
          <TargetId>
            <Identifier>i=58</Identifier>
          </TargetId>
        </ReferenceNode>
        <ReferenceNode>
          <ReferenceTypeId>
            <Identifier>i=47</Identifier>
          </ReferenceTypeId>
          <IsInverse>false</IsInverse>
          <TargetId>
            <Identifier>ns=1;i=11</Identifier>
          </TargetId>
        </ReferenceNode>
        <ReferenceNode>
          <ReferenceTypeId>
            <Identifier>i=47</Identifier>
          </ReferenceTypeId>
          <IsInverse>false</IsInverse>
          <TargetId>
            <Identifier>ns=1;i=12</Identifier>
          </TargetId>
        </ReferenceNode>
        <ReferenceNode>
          <ReferenceTypeId>
            <Identifier>i=47</Identifier>
          </ReferenceTypeId>
          <IsInverse>false</IsInverse>
          <TargetId>
            <Identifier>ns=1;i=13</Identifier>
          </TargetId>
        </ReferenceNode>
        <ReferenceNode>
          <ReferenceTypeId>
            <Identifier>i=47</Identifier>
          </ReferenceTypeId>
          <IsInverse>false</IsInverse>
          <TargetId>
            <Identifier>ns=1;i=14</Identifier>
          </TargetId>
        </ReferenceNode>
        <ReferenceNode>
          <ReferenceTypeId>
            <Identifier>i=47</Identifier>
          </ReferenceTypeId>
          <IsInverse>false</IsInverse>
          <TargetId>
            <Identifier>ns=1;i=15</Identifier>
          </TargetId>
        </ReferenceNode>
        <ReferenceNode>
          <ReferenceTypeId>
            <Identifier>i=47</Identifier>
          </ReferenceTypeId>
          <IsInverse>false</IsInverse>
          <TargetId>
            <Identifier>ns=1;i=16</Identifier>
          </TargetId>
        </ReferenceNode>
        <ReferenceNode>
          <ReferenceTypeId>
            <Identifier>i=47</Identifier>
          </ReferenceTypeId>
          <IsInverse>false</IsInverse>
          <TargetId>
            <Identifier>ns=1;i=17</Identifier>
          </TargetId>
        </ReferenceNode>
      </References>
      <EventNotifier>0</EventNotifier>
    </Node>
    <Node i:type="VariableNode">
      <NodeId>
        <Identifier>ns=1;i=11</Identifier>
      </NodeId>
      <NodeClass>Variable_2</NodeClass>
      <BrowseName>
        <NamespaceIndex>1</NamespaceIndex>
        <Name>Start</Name>
      </BrowseName>
      <DisplayName>
        <Locale></Locale>
        <Text>Start</Text>
      </DisplayName>
      <Description i:nil="true" />
      <WriteMask>0</WriteMask>
      <UserWriteMask>0</UserWriteMask>
      <RolePermissions />
      <UserRolePermissions />
      <AccessRestrictions>0</AccessRestrictions>
      <References>
        <ReferenceNode>
          <ReferenceTypeId>
            <Identifier>i=47</Identifier>
          </ReferenceTypeId>
          <IsInverse>true</IsInverse>
          <TargetId>
            <Identifier>ns=1;i=10</Identifier>
          </TargetId>
        </ReferenceNode>
        <ReferenceNode>
          <ReferenceTypeId>
            <Identifier>i=40</Identifier>
          </ReferenceTypeId>
          <IsInverse>false</IsInverse>
          <TargetId>
            <Identifier>i=63</Identifier>
          </TargetId>
        </ReferenceNode>
      </References>
      <Value>
        <Value>
          <Boolean xmlns="http://opcfoundation.org/UA/2008/02/Types.xsd">false</Boolean>
        </Value>
      </Value>
      <DataType>
        <Identifier>i=1</Identifier>
      </DataType>
      <ValueRank>-1</ValueRank>
      <ArrayDimensions />
      <AccessLevel>3</AccessLevel>
      <UserAccessLevel>3</UserAccessLevel>
      <MinimumSamplingInterval>0</MinimumSamplingInterval>
      <Historizing>false</Historizing>
      <AccessLevelEx>0</AccessLevelEx>
    </Node>
    <Node i:type="VariableNode">
      <NodeId>
        <Identifier>ns=1;i=12</Identifier>
      </NodeId>
      <NodeClass>Variable_2</NodeClass>
      <BrowseName>
        <NamespaceIndex>1</NamespaceIndex>
        <Name>Stop</Name>
      </BrowseName>
      <DisplayName>
        <Locale></Locale>
        <Text>Stop</Text>
      </DisplayName>
      <Description i:nil="true" />
      <WriteMask>0</WriteMask>
      <UserWriteMask>0</UserWriteMask>
      <RolePermissions />
      <UserRolePermissions />
      <AccessRestrictions>0</AccessRestrictions>
      <References>
        <ReferenceNode>
          <ReferenceTypeId>
            <Identifier>i=47</Identifier>
          </ReferenceTypeId>
          <IsInverse>true</IsInverse>
          <TargetId>
            <Identifier>ns=1;i=10</Identifier>
          </TargetId>
        </ReferenceNode>
        <ReferenceNode>
          <ReferenceTypeId>
            <Identifier>i=40</Identifier>
          </ReferenceTypeId>
          <IsInverse>false</IsInverse>
          <TargetId>
            <Identifier>i=63</Identifier>
          </TargetId>
        </ReferenceNode>
      </References>
      <Value>
        <Value>
          <Boolean xmlns="http://opcfoundation.org/UA/2008/02/Types.xsd">false</Boolean>
        </Value>
      </Value>
      <DataType>
        <Identifier>i=1</Identifier>
      </DataType>
      <ValueRank>-1</ValueRank>
      <ArrayDimensions />
      <AccessLevel>3</AccessLevel>
      <UserAccessLevel>3</UserAccessLevel>
      <MinimumSamplingInterval>0</MinimumSamplingInterval>
      <Historizing>false</Historizing>
      <AccessLevelEx>0</AccessLevelEx>
    </Node>
    <Node i:type="VariableNode">
      <NodeId>
        <Identifier>ns=1;i=13</Identifier>
      </NodeId>
      <NodeClass>Variable_2</NodeClass>
      <BrowseName>
        <NamespaceIndex>1</NamespaceIndex>
        <Name>Run</Name>
      </BrowseName>
      <DisplayName>
        <Locale></Locale>
        <Text>Run</Text>
      </DisplayName>
      <Description i:nil="true" />
      <WriteMask>0</WriteMask>
      <UserWriteMask>0</UserWriteMask>
      <RolePermissions />
      <UserRolePermissions />
      <AccessRestrictions>0</AccessRestrictions>
      <References>
        <ReferenceNode>
          <ReferenceTypeId>
            <Identifier>i=47</Identifier>
          </ReferenceTypeId>
          <IsInverse>true</IsInverse>
          <TargetId>
            <Identifier>ns=1;i=10</Identifier>
          </TargetId>
        </ReferenceNode>
        <ReferenceNode>
          <ReferenceTypeId>
            <Identifier>i=40</Identifier>
          </ReferenceTypeId>
          <IsInverse>false</IsInverse>
          <TargetId>
            <Identifier>i=63</Identifier>
          </TargetId>
        </ReferenceNode>
      </References>
      <Value>
        <Value>
          <Boolean xmlns="http://opcfoundation.org/UA/2008/02/Types.xsd">false</Boolean>
        </Value>
      </Value>
      <DataType>
        <Identifier>i=1</Identifier>
      </DataType>
      <ValueRank>-1</ValueRank>
      <ArrayDimensions />
      <AccessLevel>3</AccessLevel>
      <UserAccessLevel>3</UserAccessLevel>
      <MinimumSamplingInterval>0</MinimumSamplingInterval>
      <Historizing>false</Historizing>
      <AccessLevelEx>0</AccessLevelEx>
    </Node>
    <Node i:type="VariableNode">
      <NodeId>
        <Identifier>ns=1;i=14</Identifier>
      </NodeId>
      <NodeClass>Variable_2</NodeClass>
      <BrowseName>
        <NamespaceIndex>1</NamespaceIndex>
        <Name>Power</Name>
      </BrowseName>
      <DisplayName>
        <Locale></Locale>
        <Text>Power</Text>
      </DisplayName>
      <Description i:nil="true" />
      <WriteMask>0</WriteMask>
      <UserWriteMask>0</UserWriteMask>
      <RolePermissions />
      <UserRolePermissions />
      <AccessRestrictions>0</AccessRestrictions>
      <References>
        <ReferenceNode>
          <ReferenceTypeId>
            <Identifier>i=47</Identifier>
          </ReferenceTypeId>
          <IsInverse>true</IsInverse>
          <TargetId>
            <Identifier>ns=1;i=10</Identifier>
          </TargetId>
        </ReferenceNode>
        <ReferenceNode>
          <ReferenceTypeId>
            <Identifier>i=40</Identifier>
          </ReferenceTypeId>
          <IsInverse>false</IsInverse>
          <TargetId>
            <Identifier>i=63</Identifier>
          </TargetId>
        </ReferenceNode>
      </References>
      <Value>
        <Value>
          <Float xmlns="http://opcfoundation.org/UA/2008/02/Types.xsd">0</Float>
        </Value>
      </Value>
      <DataType>
        <Identifier>i=10</Identifier>
      </DataType>
      <ValueRank>-1</ValueRank>
      <ArrayDimensions />
      <AccessLevel>3</AccessLevel>
      <UserAccessLevel>3</UserAccessLevel>
      <MinimumSamplingInterval>0</MinimumSamplingInterval>
      <Historizing>false</Historizing>
      <AccessLevelEx>0</AccessLevelEx>
    </Node>
    <Node i:type="VariableNode">
      <NodeId>
        <Identifier>ns=1;i=15</Identifier>
      </NodeId>
      <NodeClass>Variable_2</NodeClass>
      <BrowseName>
        <NamespaceIndex>1</NamespaceIndex>
        <Name>PowerMax</Name>
      </BrowseName>
      <DisplayName>
        <Locale></Locale>
        <Text>PowerMax</Text>
      </DisplayName>
      <Description i:nil="true" />
      <WriteMask>0</WriteMask>
      <UserWriteMask>0</UserWriteMask>
      <RolePermissions />
      <UserRolePermissions />
      <AccessRestrictions>0</AccessRestrictions>
      <References>
        <ReferenceNode>
          <ReferenceTypeId>
            <Identifier>i=47</Identifier>
          </ReferenceTypeId>
          <IsInverse>true</IsInverse>
          <TargetId>
            <Identifier>ns=1;i=10</Identifier>
          </TargetId>
        </ReferenceNode>
        <ReferenceNode>
          <ReferenceTypeId>
            <Identifier>i=40</Identifier>
          </ReferenceTypeId>
          <IsInverse>false</IsInverse>
          <TargetId>
            <Identifier>i=63</Identifier>
          </TargetId>
        </ReferenceNode>
      </References>
      <Value>
        <Value>
          <Float xmlns="http://opcfoundation.org/UA/2008/02/Types.xsd">0</Float>
        </Value>
      </Value>
      <DataType>
        <Identifier>i=10</Identifier>
      </DataType>
      <ValueRank>-1</ValueRank>
      <ArrayDimensions />
      <AccessLevel>3</AccessLevel>
      <UserAccessLevel>3</UserAccessLevel>
      <MinimumSamplingInterval>0</MinimumSamplingInterval>
      <Historizing>false</Historizing>
      <AccessLevelEx>0</AccessLevelEx>
    </Node>
    <Node i:type="VariableNode">
      <NodeId>
        <Identifier>ns=1;i=16</Identifier>
      </NodeId>
      <NodeClass>Variable_2</NodeClass>
      <BrowseName>
        <NamespaceIndex>1</NamespaceIndex>
        <Name>Speed</Name>
      </BrowseName>
      <DisplayName>
        <Locale></Locale>
        <Text>Speed</Text>
      </DisplayName>
      <Description i:nil="true" />
      <WriteMask>0</WriteMask>
      <UserWriteMask>0</UserWriteMask>
      <RolePermissions />
      <UserRolePermissions />
      <AccessRestrictions>0</AccessRestrictions>
      <References>
        <ReferenceNode>
          <ReferenceTypeId>
            <Identifier>i=47</Identifier>
          </ReferenceTypeId>
          <IsInverse>true</IsInverse>
          <TargetId>
            <Identifier>ns=1;i=10</Identifier>
          </TargetId>
        </ReferenceNode>
        <ReferenceNode>
          <ReferenceTypeId>
            <Identifier>i=40</Identifier>
          </ReferenceTypeId>
          <IsInverse>false</IsInverse>
          <TargetId>
            <Identifier>i=63</Identifier>
          </TargetId>
        </ReferenceNode>
      </References>
      <Value>
        <Value>
          <UInt16 xmlns="http://opcfoundation.org/UA/2008/02/Types.xsd">0</UInt16>
        </Value>
      </Value>
      <DataType>
        <Identifier>i=5</Identifier>
      </DataType>
      <ValueRank>-1</ValueRank>
      <ArrayDimensions />
      <AccessLevel>3</AccessLevel>
      <UserAccessLevel>3</UserAccessLevel>
      <MinimumSamplingInterval>0</MinimumSamplingInterval>
      <Historizing>false</Historizing>
      <AccessLevelEx>0</AccessLevelEx>
    </Node>
    <Node i:type="VariableNode">
      <NodeId>
        <Identifier>ns=1;i=17</Identifier>
      </NodeId>
      <NodeClass>Variable_2</NodeClass>
      <BrowseName>
        <NamespaceIndex>1</NamespaceIndex>
        <Name>SpeedMax</Name>
      </BrowseName>
      <DisplayName>
        <Locale></Locale>
        <Text>SpeedMax</Text>
      </DisplayName>
      <Description i:nil="true" />
      <WriteMask>0</WriteMask>
      <UserWriteMask>0</UserWriteMask>
      <RolePermissions />
      <UserRolePermissions />
      <AccessRestrictions>0</AccessRestrictions>
      <References>
        <ReferenceNode>
          <ReferenceTypeId>
            <Identifier>i=47</Identifier>
          </ReferenceTypeId>
          <IsInverse>true</IsInverse>
          <TargetId>
            <Identifier>ns=1;i=10</Identifier>
          </TargetId>
        </ReferenceNode>
        <ReferenceNode>
          <ReferenceTypeId>
            <Identifier>i=40</Identifier>
          </ReferenceTypeId>
          <IsInverse>false</IsInverse>
          <TargetId>
            <Identifier>i=63</Identifier>
          </TargetId>
        </ReferenceNode>
      </References>
      <Value>
        <Value>
          <UInt16 xmlns="http://opcfoundation.org/UA/2008/02/Types.xsd">0</UInt16>
        </Value>
      </Value>
      <DataType>
        <Identifier>i=5</Identifier>
      </DataType>
      <ValueRank>-1</ValueRank>
      <ArrayDimensions />
      <AccessLevel>3</AccessLevel>
      <UserAccessLevel>3</UserAccessLevel>
      <MinimumSamplingInterval>0</MinimumSamplingInterval>
      <Historizing>false</Historizing>
      <AccessLevelEx>0</AccessLevelEx>
    </Node>
    <Node i:type="ObjectNode">
      <NodeId>
        <Identifier>ns=1;i=18</Identifier>
      </NodeId>
      <NodeClass>Object_1</NodeClass>
      <BrowseName>
        <NamespaceIndex>1</NamespaceIndex>
        <Name>Tank1</Name>
      </BrowseName>
      <DisplayName>
        <Locale></Locale>
        <Text>Tank1</Text>
      </DisplayName>
      <Description i:nil="true" />
      <WriteMask>0</WriteMask>
      <UserWriteMask>0</UserWriteMask>
      <RolePermissions />
      <UserRolePermissions />
      <AccessRestrictions>0</AccessRestrictions>
      <References>
        <ReferenceNode>
          <ReferenceTypeId>
            <Identifier>i=47</Identifier>
          </ReferenceTypeId>
          <IsInverse>true</IsInverse>
          <TargetId>
            <Identifier>ns=1;i=1</Identifier>
          </TargetId>
        </ReferenceNode>
        <ReferenceNode>
          <ReferenceTypeId>
            <Identifier>i=40</Identifier>
          </ReferenceTypeId>
          <IsInverse>false</IsInverse>
          <TargetId>
            <Identifier>i=58</Identifier>
          </TargetId>
        </ReferenceNode>
        <ReferenceNode>
          <ReferenceTypeId>
            <Identifier>i=47</Identifier>
          </ReferenceTypeId>
          <IsInverse>false</IsInverse>
          <TargetId>
            <Identifier>ns=1;i=19</Identifier>
          </TargetId>
        </ReferenceNode>
        <ReferenceNode>
          <ReferenceTypeId>
            <Identifier>i=47</Identifier>
          </ReferenceTypeId>
          <IsInverse>false</IsInverse>
          <TargetId>
            <Identifier>ns=1;i=20</Identifier>
          </TargetId>
        </ReferenceNode>
        <ReferenceNode>
          <ReferenceTypeId>
            <Identifier>i=47</Identifier>
          </ReferenceTypeId>
          <IsInverse>false</IsInverse>
          <TargetId>
            <Identifier>ns=1;i=21</Identifier>
          </TargetId>
        </ReferenceNode>
      </References>
      <EventNotifier>0</EventNotifier>
    </Node>
    <Node i:type="VariableNode">
      <NodeId>
        <Identifier>ns=1;i=19</Identifier>
      </NodeId>
      <NodeClass>Variable_2</NodeClass>
      <BrowseName>
        <NamespaceIndex>1</NamespaceIndex>
        <Name>Level</Name>
      </BrowseName>
      <DisplayName>
        <Locale></Locale>
        <Text>Level</Text>
      </DisplayName>
      <Description i:nil="true" />
      <WriteMask>0</WriteMask>
      <UserWriteMask>0</UserWriteMask>
      <RolePermissions />
      <UserRolePermissions />
      <AccessRestrictions>0</AccessRestrictions>
      <References>
        <ReferenceNode>
          <ReferenceTypeId>
            <Identifier>i=47</Identifier>
          </ReferenceTypeId>
          <IsInverse>true</IsInverse>
          <TargetId>
            <Identifier>ns=1;i=18</Identifier>
          </TargetId>
        </ReferenceNode>
        <ReferenceNode>
          <ReferenceTypeId>
            <Identifier>i=40</Identifier>
          </ReferenceTypeId>
          <IsInverse>false</IsInverse>
          <TargetId>
            <Identifier>i=63</Identifier>
          </TargetId>
        </ReferenceNode>
      </References>
      <Value>
        <Value>
          <Float xmlns="http://opcfoundation.org/UA/2008/02/Types.xsd">0</Float>
        </Value>
      </Value>
      <DataType>
        <Identifier>i=10</Identifier>
      </DataType>
      <ValueRank>-1</ValueRank>
      <ArrayDimensions />
      <AccessLevel>3</AccessLevel>
      <UserAccessLevel>3</UserAccessLevel>
      <MinimumSamplingInterval>0</MinimumSamplingInterval>
      <Historizing>false</Historizing>
      <AccessLevelEx>0</AccessLevelEx>
    </Node>
    <Node i:type="VariableNode">
      <NodeId>
        <Identifier>ns=1;i=20</Identifier>
      </NodeId>
      <NodeClass>Variable_2</NodeClass>
      <BrowseName>
        <NamespaceIndex>1</NamespaceIndex>
        <Name>High</Name>
      </BrowseName>
      <DisplayName>
        <Locale></Locale>
        <Text>High</Text>
      </DisplayName>
      <Description i:nil="true" />
      <WriteMask>0</WriteMask>
      <UserWriteMask>0</UserWriteMask>
      <RolePermissions />
      <UserRolePermissions />
      <AccessRestrictions>0</AccessRestrictions>
      <References>
        <ReferenceNode>
          <ReferenceTypeId>
            <Identifier>i=47</Identifier>
          </ReferenceTypeId>
          <IsInverse>true</IsInverse>
          <TargetId>
            <Identifier>ns=1;i=18</Identifier>
          </TargetId>
        </ReferenceNode>
        <ReferenceNode>
          <ReferenceTypeId>
            <Identifier>i=40</Identifier>
          </ReferenceTypeId>
          <IsInverse>false</IsInverse>
          <TargetId>
            <Identifier>i=63</Identifier>
          </TargetId>
        </ReferenceNode>
      </References>
      <Value>
        <Value>
          <Boolean xmlns="http://opcfoundation.org/UA/2008/02/Types.xsd">false</Boolean>
        </Value>
      </Value>
      <DataType>
        <Identifier>i=1</Identifier>
      </DataType>
      <ValueRank>-1</ValueRank>
      <ArrayDimensions />
      <AccessLevel>3</AccessLevel>
      <UserAccessLevel>3</UserAccessLevel>
      <MinimumSamplingInterval>0</MinimumSamplingInterval>
      <Historizing>false</Historizing>
      <AccessLevelEx>0</AccessLevelEx>
    </Node>
    <Node i:type="VariableNode">
      <NodeId>
        <Identifier>ns=1;i=21</Identifier>
      </NodeId>
      <NodeClass>Variable_2</NodeClass>
      <BrowseName>
        <NamespaceIndex>1</NamespaceIndex>
        <Name>Low</Name>
      </BrowseName>
      <DisplayName>
        <Locale></Locale>
        <Text>Low</Text>
      </DisplayName>
      <Description i:nil="true" />
      <WriteMask>0</WriteMask>
      <UserWriteMask>0</UserWriteMask>
      <RolePermissions />
      <UserRolePermissions />
      <AccessRestrictions>0</AccessRestrictions>
      <References>
        <ReferenceNode>
          <ReferenceTypeId>
            <Identifier>i=47</Identifier>
          </ReferenceTypeId>
          <IsInverse>true</IsInverse>
          <TargetId>
            <Identifier>ns=1;i=18</Identifier>
          </TargetId>
        </ReferenceNode>
        <ReferenceNode>
          <ReferenceTypeId>
            <Identifier>i=40</Identifier>
          </ReferenceTypeId>
          <IsInverse>false</IsInverse>
          <TargetId>
            <Identifier>i=63</Identifier>
          </TargetId>
        </ReferenceNode>
      </References>
      <Value>
        <Value>
          <Boolean xmlns="http://opcfoundation.org/UA/2008/02/Types.xsd">false</Boolean>
        </Value>
      </Value>
      <DataType>
        <Identifier>i=1</Identifier>
      </DataType>
      <ValueRank>-1</ValueRank>
      <ArrayDimensions />
      <AccessLevel>3</AccessLevel>
      <UserAccessLevel>3</UserAccessLevel>
      <MinimumSamplingInterval>0</MinimumSamplingInterval>
      <Historizing>false</Historizing>
      <AccessLevelEx>0</AccessLevelEx>
    </Node>
  </Nodes>
</NodeSet>